pytest_odoo.py
pytest_odoo-2.1.3.dist-info/licenses/LICENSE
pytest_odoo-2.1.3.dist-info/METADATA
pytest_odoo-2.1.3.dist-info/WHEEL
pytest_odoo-2.1.3.dist-info/entry_points.txt
pytest_odoo-2.1.3.dist-info/top_level.txt
pytest_odoo-2.1.3.dist-info/RECORD
